odoo/addons/crm_group_sale_salesman_extension/README.rst
odoo/addons/crm_group_sale_salesman_extension/__init__.py
odoo/addons/crm_group_sale_salesman_extension/__manifest__.py
odoo/addons/crm_group_sale_salesman_extension/readme/CONFIGURE.md
odoo/addons/crm_group_sale_salesman_extension/readme/CONTRIBUTORS.md
odoo/addons/crm_group_sale_salesman_extension/readme/DESCRIPTION.md
odoo/addons/crm_group_sale_salesman_extension/readme/INSTALL.md
odoo/addons/crm_group_sale_salesman_extension/readme/USAGE.md
odoo/addons/crm_group_sale_salesman_extension/security/crm_sale_record_rules.xml
odoo/addons/crm_group_sale_salesman_extension/static/description/icon.png
odoo/addons/crm_group_sale_salesman_extension/static/description/index.html
odoo_addon_crm_group_sale_salesman_extension-18.0.1.0.0.dist-info/METADATA
odoo_addon_crm_group_sale_salesman_extension-18.0.1.0.0.dist-info/WHEEL
odoo_addon_crm_group_sale_salesman_extension-18.0.1.0.0.dist-info/top_level.txt
odoo_addon_crm_group_sale_salesman_extension-18.0.1.0.0.dist-info/RECORD
