Metadata-Version: 2.1
Name: odoo-addon-crm_group_sale_salesman_extension
Version: 18.0.1.0.0
Requires-Python: >=3.10
Requires-Dist: odoo==18.0.*
Summary: CRM Group Sale Salesman Extension
Home-page: https://github.com/sygel-technology/sy-crm
License: AGPL-3
Author: Sygel, Odoo Community Association (OCA)
Author-email: support@odoo-community.org
Classifier: Programming Language :: Python
Classifier: Framework :: Odoo
Classifier: Framework :: Odoo :: 18.0
Classifier: License :: OSI Approved :: GNU Affero General Public License v3
